bangla_character/__init__.py
bangla_character/bangla.py
bangla_character-0.0.1.dist-info/LICENCE
bangla_character-0.0.1.dist-info/METADATA
bangla_character-0.0.1.dist-info/WHEEL
bangla_character-0.0.1.dist-info/top_level.txt
bangla_character-0.0.1.dist-info/RECORD
