Metadata-Version: 2.1
Name: bangla-character
Version: 0.0.1
Summary: For generating Bangla Character using index
Home-page: https://github.com/awmium/Bangla-Characters-Pypi
Author: Azmir Murad
Author-email: awmium@gmail.com
Classifier: Programming Language :: Python :: 3
Classifier: License :: OSI Approved :: MIT License
Classifier: Operating System :: OS Independent
Requires-Python: >=3.7
License-File: LICENCE
